heaserver/dataadapter/__init__.py
heaserver/dataadapter/service.py
heaserver/dataadapter/wstl/all.json
heaserver_data_adapters-1.0.0a24.dist-info/LICENSE
heaserver_data_adapters-1.0.0a24.dist-info/METADATA
heaserver_data_adapters-1.0.0a24.dist-info/WHEEL
heaserver_data_adapters-1.0.0a24.dist-info/entry_points.txt
heaserver_data_adapters-1.0.0a24.dist-info/top_level.txt
heaserver_data_adapters-1.0.0a24.dist-info/RECORD
