Metadata-Version: 2.1
Name: heaserver-data-adapters
Version: 1.0.0a24
Summary: The HEA data adapter service.
Home-page: https://risr.hci.utah.edu
Author: Research Informatics Shared Resource, Huntsman Cancer Institute, Salt Lake City, UT
Author-email: Andrew.Post@hci.utah.edu
License: UNKNOWN
Platform: UNKNOWN
Classifier: Development Status :: 2 - Pre-Alpha
Classifier: Intended Audience :: Developers
Classifier: Intended Audience :: Science/Research
Classifier: License :: OSI Approved :: Apache Software License
Classifier: Framework :: AsyncIO
Classifier: Environment :: Web Environment
Classifier: Natural Language :: English
Classifier: Operating System :: OS Independent
Classifier: Programming Language :: Python :: 3
Classifier: Programming Language :: Python :: 3.10
Classifier: Topic :: Software Development
Classifier: Topic :: Scientific/Engineering
Classifier: Topic :: Scientific/Engineering :: Bio-Informatics
Classifier: Topic :: Scientific/Engineering :: Information Analysis
Classifier: Topic :: Scientific/Engineering :: Medical Science Apps.
Requires-Python: >=3.10
License-File: LICENSE
Requires-Dist: heaserver (<1.0.0a77,>=1.0.0a76)
